alara_split_gather/__init__.py
alara_split_gather/alara_gather_tasks.py
alara_split_gather/alara_split_task.py
alara_split_gather/check_tasks_status.py
alara_split_gather/gather_alara_task.py
alara_split_gather/split_alara_task.py
alara_split_gather/utils.py
alara_split_gather-0.1.8.dist-info/LICENSE
alara_split_gather-0.1.8.dist-info/METADATA
alara_split_gather-0.1.8.dist-info/WHEEL
alara_split_gather-0.1.8.dist-info/entry_points.txt
alara_split_gather-0.1.8.dist-info/top_level.txt
alara_split_gather-0.1.8.dist-info/RECORD
