Metadata-Version: 2.1
Name: alara-split-gather
Version: 0.1.8
Summary: Python package to split and gather ALARA tasks
Home-page: https://github.com/zxkjack123/alara_split_gather
Author: Xiaokang Zhang
Author-email: zxkjack123@163.com
License: MIT
Platform: UNKNOWN
Classifier: Programming Language :: Python :: 3
Classifier: License :: OSI Approved :: MIT License
Classifier: Operating System :: OS Independent
Classifier: Environment :: Console
Requires-Python: >=3.6
